pipes/__init__.py
pipes/client.py
pipes/inference.py
pipes/json_utils.py
pipes/server.py
skilpipes/__init__.py
skilpipes/client.py
skilpipes/inference.py
skilpipes/json_utils.py
skilpipes/server.py
skymind_pipelines-0.1.dist-info/DESCRIPTION.rst
skymind_pipelines-0.1.dist-info/METADATA
skymind_pipelines-0.1.dist-info/RECORD
skymind_pipelines-0.1.dist-info/WHEEL
skymind_pipelines-0.1.dist-info/metadata.json
skymind_pipelines-0.1.dist-info/top_level.txt
tests/__init__.py
tests/test_bert_serving.py
tests/test_client_serde.py
tests/test_json.py
tests/test_python_serving.py
tests/test_start.py
tests/test_transform_process.py
tests/test_transform_process_arrow.py
tests/utils.py
