Metadata-Version: 2.0
Name: skymind-pipelines
Version: 0.1
Summary: pipelines: Deploy your machine learning experiments with Skymind Pipelines
Home-page: https://github.com/SkymindIO/pipelines
Author: Max Pumperla
Author-email: max@skymind.io
License: Apache
Platform: UNKNOWN
Classifier: Development Status :: 3 - Alpha
Classifier: Intended Audience :: Developers
Classifier: Environment :: Console
Classifier: License :: OSI Approved :: Apache Software License
Classifier: Operating System :: OS Independent
Classifier: Programming Language :: Python
Classifier: Programming Language :: Python :: 2
Classifier: Programming Language :: Python :: 3
Provides-Extra: tests
Requires-Dist: requests (>=2.22.0)
Requires-Dist: numpy (<=1.16.4)
Requires-Dist: pyarrow (==0.13.0)
Requires-Dist: requests-toolbelt (>=0.9.1)
Requires-Dist: pandas (<=0.24.2)
Provides-Extra: tests
Requires-Dist: pyjnius; extra == 'tests'
Requires-Dist: pytest; extra == 'tests'
Requires-Dist: pytest-pep8; extra == 'tests'
Requires-Dist: pytest-cov; extra == 'tests'
Requires-Dist: mock; extra == 'tests'
Requires-Dist: pydatavec; extra == 'tests'
